LICENSE
README.md
setup.cfg
setup.py
opencv_wrapper/__init__.py
opencv_wrapper/__version__.py
opencv_wrapper/display.py
opencv_wrapper/image_operations.py
opencv_wrapper/misc_functions.py
opencv_wrapper/model.py
opencv_wrapper/tracking.py
opencv_wrapper/utils.py
opencv_wrapper/video.py
opencv_wrapper.egg-info/PKG-INFO
opencv_wrapper.egg-info/SOURCES.txt
opencv_wrapper.egg-info/dependency_links.txt
opencv_wrapper.egg-info/requires.txt
opencv_wrapper.egg-info/top_level.txt