Metadata-Version: 2.1
Name: opencv-wrapper
Version: 0.2.1
Summary: A Python wrapper for OpenCV.
Home-page: https://github.com/anbergem/opencv_wrapper
Author: Andreas Bergem
Author-email: bergem.andreas@gmail.com
License: MIT
Keywords: OpenCV
Platform: UNKNOWN
Classifier: Intended Audience :: Developers
Classifier: License :: OSI Approved :: MIT License
Classifier: Natural Language :: English
Classifier: Operating System :: OS Independent
Classifier: Programming Language :: Python :: 3.6
Classifier: Programming Language :: Python :: 3.7
Classifier: Topic :: Scientific/Engineering
Classifier: Topic :: Scientific/Engineering :: Image Recognition
Classifier: Typing :: Typed
Requires-Python: >=3.6
